hive_4_api_client/__init__.py
hive_4_api_client/api_client.py
hive_4_api_client/api_response.py
hive_4_api_client/configuration.py
hive_4_api_client/exceptions.py
hive_4_api_client/py.typed
hive_4_api_client/rest.py
hive_4_api_client/api/__init__.py
hive_4_api_client/api/pet_api.py
hive_4_api_client/api/store_api.py
hive_4_api_client/api/user_api.py
hive_4_api_client/models/__init__.py
hive_4_api_client/models/address.py
hive_4_api_client/models/api_response.py
hive_4_api_client/models/category.py
hive_4_api_client/models/customer.py
hive_4_api_client/models/order.py
hive_4_api_client/models/pet.py
hive_4_api_client/models/tag.py
hive_4_api_client/models/user.py
hive_4_api_client-1.0.0.dist-info/METADATA
hive_4_api_client-1.0.0.dist-info/WHEEL
hive_4_api_client-1.0.0.dist-info/top_level.txt
hive_4_api_client-1.0.0.dist-info/RECORD
